bottletools/__init__.py
bottletools/indextools.py
bottletools/s3tools.py
bottletools-0.0.3.dist-info/LICENSE.txt
bottletools-0.0.3.dist-info/METADATA
bottletools-0.0.3.dist-info/WHEEL
bottletools-0.0.3.dist-info/top_level.txt
bottletools-0.0.3.dist-info/RECORD
