Metadata-Version: 2.1
Name: bottletools
Version: 0.0.3
Summary: Bottle tools
Home-page: https://gitlab.com/smartad/bottletools
Author: Bikash Sapkota
Author-email: bikash@bottle.com.np
License: MIT
Download-URL: https://pypi.org/project/bottletools/
Keywords: aws,bottle,nepal
Platform: UNKNOWN
Requires-Dist: boto3
